loader/__init__.py
loader/__main__.py
loader/cli.py
loader/download.py
YouTube_Loader-0.3.dist-info/LICENSE
YouTube_Loader-0.3.dist-info/METADATA
YouTube_Loader-0.3.dist-info/WHEEL
YouTube_Loader-0.3.dist-info/entry_points.txt
YouTube_Loader-0.3.dist-info/top_level.txt
YouTube_Loader-0.3.dist-info/RECORD
